[
  {
    "Modello": "altre",
    "Immatricolazioni": "589"
  },
  {
    "Modello": "Hyundai Kona",
    "Immatricolazioni": "134"
  },
  {
    "Modello": "Nissan Leaf",
    "Immatricolazioni": "142"
  },
  {
    "Modello": "Opel Corsa",
    "Immatricolazioni": "157"
  },
  {
    "Modello": "Peugeot 2008",
    "Immatricolazioni": "163"
  },
  {
    "Modello": "Peugeot 208",
    "Immatricolazioni": "184"
  },
  {
    "Modello": "Tesla Model 3",
    "Immatricolazioni": "278"
  },
  {
    "Modello": "Renault Zoe",
    "Immatricolazioni": "296"
  },
  {
    "Modello": "Renault Twingo",
    "Immatricolazioni": "386"
  },

  {
    "Modello": "Smart Fortwo",
    "Immatricolazioni": "545"
  },
  {
    "Modello": "Fiat 500",
    "Immatricolazioni": "583"
  }
]
